komodo_rpc.py
komodo/__init__.py
komodo/address.py
komodo/blockchain.py
komodo/control.py
komodo/disclosure.py
komodo/generate.py
komodo/jumblr.py
komodo/mining.py
komodo/network.py
komodo/raw_transactions.py
komodo/util.py
komodo/wallet.py
rpc_util/__init__.py
rpc_util/rpc.py
komodorpc-1.0.dist-info/LICENSE
komodorpc-1.0.dist-info/METADATA
komodorpc-1.0.dist-info/WHEEL
komodorpc-1.0.dist-info/top_level.txt
komodorpc-1.0.dist-info/RECORD
