Metadata-Version: 2.1
Name: komodorpc
Version: 1.0
Summary: RPC API-Library for Komodo-based asset chains, for Python DApp Developers
Home-page: https://github.com/V413H4V/Komodo-RPC-Library-Python/
Author: Vaibhav Murkute
Author-email: vaibhavmurkute88@gmail.com
License: MIT
Keywords: komodorpc,komodo
Platform: UNKNOWN
Classifier: Programming Language :: Python :: 3
Classifier: Programming Language :: Python :: 3.7
Classifier: License :: OSI Approved :: MIT License
Classifier: Operating System :: OS Independent
Requires-Dist: requests (>=2.22.0)
